{"key":"store","content":{"nodeType":"translation","translation":{"en":{"ui":{"storeNotFound":"Store not found","recentlyBought":"Recently bought items","reviews":"Reviews","more":"More","searchIn":"Search in","noProducts":"No products found for this store.","deals":"Deals","products":"Products"},"banner":{"delivery":"Delivery","pickup":"Pickup","min":"min","openUntil":"Open until","minOrder":"Min. order","restaurantDetails":"Restaurant details","scheduleOrder":"Schedule order","orderTogether":"Order together"},"reviews":{"reviewsTitle":"Reviews","rateExperience":"Rate your experience","yourReview":"Your review","placeholder":"Tell others about the food and service...","postReview":"Post review","loginPrompt":"Please log in to leave a review","login":"Login","noReviewsYet":"No reviews yet. Be the first!","error":"An error occurred while sending the review. Please log in again."},"productModal":{"weight":"Weight:","unitPrice":"Unit Price:","addToOrder":"Add to order"}},"tr":{"ui":{"storeNotFound":"Mağaza bulunamadı","recentlyBought":"Son satın alınan ürünler","reviews":"Değerlendirmeler","more":"Daha fazla","searchIn":"Ara:","noProducts":"Bu mağaza için ürün bulunamadı.","deals":"Fırsatlar","products":"Ürünler"},"banner":{"delivery":"Teslimat","pickup":"Gel-al","min":"dk","openUntil":"Kapanış:","minOrder":"Min. sipariş","restaurantDetails":"Restoran detayları","scheduleOrder":"Sipariş planla","orderTogether":"Birlikte sipariş ver"},"reviews":{"reviewsTitle":"Değerlendirmeler","rateExperience":"Deneyiminizi puanlayın","yourReview":"Yorumunuz","placeholder":"Yemek ve hizmet hakkında başkalarına bilsi verin...","postReview":"Yorum yap","loginPrompt":"Yorum yapmak için lütfen giriş yapın","login":"Giriş yap","noReviewsYet":"Henüz yorum yok. İlk siz olun!","error":"Rəy göndərilərkən xəta baş verdi. Zəhmət olmasa yenidən daxil olun."},"productModal":{"weight":"Ağırlık:","unitPrice":"Birim Fiyat:","addToOrder":"Siparişe ekle"}}}},"localIds":["store::local::components\\View\\main\\storeView\\store.content.ts"]}